odoo/addons/pos_supplierinfo_barcode/README.rst
odoo/addons/pos_supplierinfo_barcode/__init__.py
odoo/addons/pos_supplierinfo_barcode/__manifest__.py
odoo/addons/pos_supplierinfo_barcode/i18n/es.po
odoo/addons/pos_supplierinfo_barcode/i18n/it.po
odoo/addons/pos_supplierinfo_barcode/i18n/pos_supplierinfo_barcode.pot
odoo/addons/pos_supplierinfo_barcode/models/__init__.py
odoo/addons/pos_supplierinfo_barcode/models/product.py
odoo/addons/pos_supplierinfo_barcode/readme/CONFIGURE.rst
odoo/addons/pos_supplierinfo_barcode/readme/CONTRIBUTORS.rst
odoo/addons/pos_supplierinfo_barcode/readme/DESCRIPTION.rst
odoo/addons/pos_supplierinfo_barcode/readme/USAGE.rst
odoo/addons/pos_supplierinfo_barcode/static/description/icon.png
odoo/addons/pos_supplierinfo_barcode/static/description/index.html
odoo/addons/pos_supplierinfo_barcode/static/src/js/db.js
odoo/addons/pos_supplierinfo_barcode/views/assets.xml
odoo12_addon_pos_supplierinfo_barcode-12.0.1.0.0.99.dev10.dist-info/METADATA
odoo12_addon_pos_supplierinfo_barcode-12.0.1.0.0.99.dev10.dist-info/WHEEL
odoo12_addon_pos_supplierinfo_barcode-12.0.1.0.0.99.dev10.dist-info/top_level.txt
odoo12_addon_pos_supplierinfo_barcode-12.0.1.0.0.99.dev10.dist-info/RECORD
